[
  {
    "ContainingType": "PureCosmetics.AuthService.Api.Controllers.AuthController",
    "Method": "CreateUser",
    "RelativePath": "api/Auth/CreateUser",
    "HttpMethod": "POST",
    "IsController": true,
    "Order": 0,
    "Parameters": [
      {
        "Name": "request",
        "Type": "PureCosmetics.AuthService.Application.Models.Requests.User.UserCreateRequest",
        "IsRequired": true
      }
    ],
    "ReturnTypes": []
  },
  {
    "ContainingType": "PureCosmetics.AuthService.Api.Controllers.AuthController",
    "Method": "DebugJwt",
    "RelativePath": "api/Auth/DebugJwt",
    "HttpMethod": "POST",
    "IsController": true,
    "Order": 0,
    "Parameters": [
      {
        "Name": "token",
        "Type": "System.String",
        "IsRequired": true
      }
    ],
    "ReturnTypes": []
  },
  {
    "ContainingType": "PureCosmetics.AuthService.Api.Controllers.AuthController",
    "Method": "DeleteUser",
    "RelativePath": "api/Auth/DeleteUser",
    "HttpMethod": "PUT",
    "IsController": true,
    "Order": 0,
    "Parameters": [
      {
        "Name": "request",
        "Type": "PureCosmetics.AuthService.Application.Models.Requests.User.UserDeleteRequest",
        "IsRequired": true
      }
    ],
    "ReturnTypes": []
  },
  {
    "ContainingType": "PureCosmetics.AuthService.Api.Controllers.AuthController",
    "Method": "GetAllUsers",
    "RelativePath": "api/Auth/GetAllUsers",
    "HttpMethod": "GET",
    "IsController": true,
    "Order": 0,
    "Parameters": [
      {
        "Name": "request",
        "Type": "PureCosmetics.AuthService.Application.Models.Requests.User.UserGetsRequest",
        "IsRequired": true
      }
    ],
    "ReturnTypes": []
  },
  {
    "ContainingType": "PureCosmetics.AuthService.Api.Controllers.AuthController",
    "Method": "GetUserById",
    "RelativePath": "api/Auth/GetUserById",
    "HttpMethod": "GET",
    "IsController": true,
    "Order": 0,
    "Parameters": [
      {
        "Name": "request",
        "Type": "PureCosmetics.AuthService.Application.Models.Requests.User.UserGetByIdRequest",
        "IsRequired": true
      }
    ],
    "ReturnTypes": []
  },
  {
    "ContainingType": "PureCosmetics.AuthService.Api.Controllers.AuthController",
    "Method": "Login",
    "RelativePath": "api/Auth/Login",
    "HttpMethod": "POST",
    "IsController": true,
    "Order": 0,
    "Parameters": [
      {
        "Name": "request",
        "Type": "PureCosmetics.AuthService.Application.Models.Requests.User.UserLoginRequest",
        "IsRequired": true
      }
    ],
    "ReturnTypes": []
  },
  {
    "ContainingType": "PureCosmetics.AuthService.Api.Controllers.AuthController",
    "Method": "UpdateUser",
    "RelativePath": "api/Auth/UpdateUser",
    "HttpMethod": "PUT",
    "IsController": true,
    "Order": 0,
    "Parameters": [
      {
        "Name": "request",
        "Type": "PureCosmetics.AuthService.Application.Models.Requests.User.UserUpdateRequest",
        "IsRequired": true
      }
    ],
    "ReturnTypes": []
  }
]